{
  "Object": {
    "GUID": "a25766",
    "Name": "Custom_Model",
    "Transform": {
      "posX": 17.37962,
      "posY": 1.010085,
      "posZ": -65.62725,
      "rotX": 0.000009763993,
      "rotY": 269.999481,
      "rotZ": 0.00000665181824,
      "scaleX": 0.62499994,
      "scaleY": 0.62499994,
      "scaleZ": 0.62499994
    },
    "Nickname": "Shadow Leading Player Counter",
    "Description": "",
    "GMNotes": "",
    "AltLookAngle": {
      "x": 0,
      "y": 0,
      "z": 0
    },
    "ColorDiffuse": {
      "r": 1,
      "g": 1,
      "b": 0.9960827
    },
    "LayoutGroupSortIndex": 0,
    "Value": 0,
    "Locked": false,
    "Grid": true,
    "Snap": true,
    "IgnoreFoW": false,
    "MeasureMovement": false,
    "DragSelectable": true,
    "Autoraise": true,
    "Sticky": true,
    "Tooltip": true,
    "GridProjection": false,
    "HideWhenFaceDown": false,
    "Hands": false,
    "CustomMesh": {
      "MeshURL": "http://cloud-3.steamusercontent.com/ugc/1666862284380840235/5B6FFFDCDFE2D441DA5E3AB2D831A2CE5ECB6AC5/",
      "DiffuseURL": "http://cloud-3.steamusercontent.com/ugc/1666862284381105742/E83E3ACB2287D5A43B09576885A900F8BAA697FD/",
      "NormalURL": "",
      "ColliderURL": "",
      "Convex": true,
      "MaterialIndex": 3,
      "TypeIndex": 4,
      "CustomShader": {
        "SpecularColor": {
          "r": 1,
          "g": 1,
          "b": 1
        },
        "SpecularIntensity": 0,
        "SpecularSharpness": 2,
        "FresnelStrength": 0
      },
      "CastShadows": true
    },
    "LuaScript": "",
    "LuaScriptState": "",
    "XmlUI": ""
  },
  "StatesPaths": {}
}
