{
    "Object": {
        "GUID": "647b1f",
        "Name": "Card",
        "Transform": {
            "posX": -43.57,
            "posY": 2.54,
            "posZ": 37.93,
            "rotX": 0,
            "rotY": 180,
            "rotZ": 0,
            "scaleX": 2.8,
            "scaleY": 1,
            "scaleZ": 2.8
        },
        "Nickname": "By Chance or by Foresight",
        "Description": "Card;Faction;FreePeoples;#19;WoME;",
        "GMNotes": "",
        "AltLookAngle": {
            "x": 0,
            "y": 0,
            "z": 0
        },
        "ColorDiffuse": {
            "r": 1,
            "g": 1,
            "b": 1
        },
        "LayoutGroupSortIndex": 0,
        "Value": 0,
        "Locked": false,
        "Grid": true,
        "Snap": true,
        "IgnoreFoW": false,
        "MeasureMovement": false,
        "DragSelectable": true,
        "Autoraise": true,
        "Sticky": true,
        "Tooltip": true,
        "GridProjection": false,
        "HideWhenFaceDown": true,
        "Hands": true,
        "CardID": 206718,
        "SidewaysCard": false,
        "CustomDeck": {
            "8": {
                "FaceURL": "https://steamusercontent-a.akamaihd.net/ugc/2449475694172489580/D2CF71D1AF10397010205667454EB08457FE0E1C/",
                "BackURL": "https://steamusercontent-a.akamaihd.net/ugc/1836922259142899143/7BBDDCBDC8A1ACDD8069CD94BDFBE3BD8B90756F/",
                "NumWidth": 9,
                "NumHeight": 5,
                "BackIsHidden": true,
                "UniqueBack": false,
                "Type": 0
            }
        },
        "LuaScript": "",
        "LuaScriptState": "",
        "XmlUI": ""
    },
    "StatesPaths": {}
}
